sparkplug_foo/__init__.py
sparkplug_foo-0.0.1.dist-info/METADATA
sparkplug_foo-0.0.1.dist-info/WHEEL
sparkplug_foo-0.0.1.dist-info/RECORD
